[
  {
    "title": "Happy Fun Times",
    "description": "Toys. Vokriinator Black. AE. LOTD. New Enemies. More Dungeons. Fun Times.",
    "author": "Total",
    "maintainers": [
      "github/NotTotal"
    ],
    "game": "skyrimspecialedition",
    "official": false,
    "tags": [
      "Creation Club",
      "Anniversary Edition",
      "Legacy of the Dragonborn",
      "LotD",
      "NSFW"
    ],
    "nsfw": true,
    "utility_list": false,
    "image_contains_title": false,
    "force_down": false,
    "links": {
      "image": "https://raw.githubusercontent.com/NotTotal/Happy-fun-times/main/SkyrimSE_t6C0mxuRWU.webp",
      "readme": "https://raw.githubusercontent.com/NotTotal/Happy-fun-times/main/README.md",
      "download": "https://authored-files.wabbajack.org/Happy Fun Times.wabbajack_0bf644fd-981b-4746-949c-6ae2abc4afde",
      "machineURL": "HFT",
      "discordURL": "https://discord.gg/jolly-coop"
    },
    "download_metadata": {
      "Hash": "h60LkSOyNZo=",
      "Size": 296874370,
      "NumberOfArchives": 1906,
      "SizeOfArchives": 176760310374,
      "NumberOfInstalledFiles": 232963,
      "SizeOfInstalledFiles": 333827911960
    },
    "version": "0.8.0",
    "dateCreated": "1970-01-01T00:00:00Z",
    "dateUpdated": "2022-12-08T16:16:26.6560634Z",
    "repositoryName": ""
  }
]